dataset_toolkit/__init__.py
dataset_toolkit/models.py
dataset_toolkit/pipeline.py
dataset_toolkit/exporters/__init__.py
dataset_toolkit/exporters/coco_exporter.py
dataset_toolkit/exporters/txt_exporter.py
dataset_toolkit/exporters/yolo_exporter.py
dataset_toolkit/loaders/__init__.py
dataset_toolkit/loaders/local_loader.py
dataset_toolkit/processors/__init__.py
dataset_toolkit/processors/evaluator.py
dataset_toolkit/processors/merger.py
dataset_toolkit/utils/__init__.py
dataset_toolkit/utils/coords.py
dataset_toolkit-0.2.0.dist-info/licenses/LICENSE
dataset_toolkit-0.2.0.dist-info/METADATA
dataset_toolkit-0.2.0.dist-info/WHEEL
dataset_toolkit-0.2.0.dist-info/top_level.txt
dataset_toolkit-0.2.0.dist-info/RECORD
