Metadata-Version: 2.4
Name: dataset-toolkit
Version: 0.2.0
Summary: 一个用于加载、处理和导出计算机视觉数据集的工具包
Home-page: https://github.com/yourusername/dataset-toolkit
Author: wenxiang.han
Author-email: "wenxiang.han" <wenxiang.han@anker-in.com>
License: MIT
Project-URL: Homepage, https://github.com/yourusername/dataset-toolkit
Project-URL: Documentation, https://dataset-toolkit.readthedocs.io
Project-URL: Repository, https://github.com/yourusername/dataset-toolkit
Project-URL: Bug Tracker, https://github.com/yourusername/dataset-toolkit/issues
Keywords: computer vision,dataset,yolo,coco,machine learning
Classifier: Development Status :: 3 - Alpha
Classifier: Intended Audience :: Developers
Classifier: Topic :: Software Development :: Libraries :: Python Modules
Classifier: Topic :: Scientific/Engineering :: Artificial Intelligence
Classifier: License :: OSI Approved :: MIT License
Classifier: Programming Language :: Python :: 3
Requires-Python: >=3.7
License-File: LICENSE
Requires-Dist: Pillow>=8.0.0
Provides-Extra: dev
Requires-Dist: pytest>=6.0; extra == "dev"
Requires-Dist: pytest-cov>=2.0; extra == "dev"
Requires-Dist: black>=21.0; extra == "dev"
Requires-Dist: flake8>=3.9; extra == "dev"
Dynamic: author
Dynamic: home-page
Dynamic: license-file
Dynamic: requires-python
